minecraft_python-161348.dist-info/LICENSE
minecraft_python-161348.dist-info/top_level.txt
minecraft_python-161348.dist-info/RECORD
minecraft_python-161348.dist-info/METADATA
minecraft_python-161348.dist-info/WHEEL
mc/Resources.py
mc/CompatibilityShims.py
mc/__init__.py
mc/net/__init__.py
mc/net/minecraft/Entity.py
mc/net/minecraft/Textures.py
mc/net/minecraft/Player.py
mc/net/minecraft/Timer.py
mc/net/minecraft/Minecraft.py
mc/net/minecraft/HitResult.py
mc/net/minecraft/__init__.py
mc/net/minecraft/level/Chunk.cpython-310-x86_64-linux-gnu.so
mc/net/minecraft/level/Frustum.cpython-310-x86_64-linux-gnu.so
mc/net/minecraft/level/DirtyChunkSorter.py
mc/net/minecraft/level/Tesselator.cpython-310-x86_64-linux-gnu.so
mc/net/minecraft/level/PerlinNoiseFilter.py
mc/net/minecraft/level/LevelListener.py
mc/net/minecraft/level/Level.cpython-310-x86_64-linux-gnu.so
mc/net/minecraft/level/LevelRenderer.py
mc/net/minecraft/level/__init__.py
mc/net/minecraft/level/tile/GrassTile.py
mc/net/minecraft/level/tile/Tiles.cpython-310-x86_64-linux-gnu.so
mc/net/minecraft/level/tile/Tile.cpython-310-x86_64-linux-gnu.so
mc/net/minecraft/level/tile/Bush.py
mc/net/minecraft/level/tile/__init__.py
mc/net/minecraft/level/tile/DirtTile.py
mc/net/minecraft/particle/Particle.py
mc/net/minecraft/particle/ParticleEngine.py
mc/net/minecraft/particle/__init__.py
mc/net/minecraft/phys/AABB.py
mc/net/minecraft/phys/__init__.py
mc/net/minecraft/character/Vertex.py
mc/net/minecraft/character/Vec3.py
mc/net/minecraft/character/Zombie.py
mc/net/minecraft/character/Cube.py
mc/net/minecraft/character/ZombieModel.py
mc/net/minecraft/character/Polygon.py
mc/net/minecraft/character/__init__.py
