Metadata-Version: 2.1
Name: minecraft-python
Version: 161348
Summary: A project that seeks to recreate every old Minecraft version in Python using Pyglet and Cython.
Home-page: https://github.com/pythonengineer/minecraft-python
Download-URL: https://pypi.org/project/minecraft-python
Author: pythonengineer
License: BSD
Project-URL: Source, https://github.com/pythonengineer/minecraft-python
Project-URL: Tracker, https://github.com/pythonengineer/minecraft-python/issues
Keywords: minecraft pyglet cython sandbox game classic
Classifier: Development Status :: 5 - Production/Stable
Classifier: Environment :: MacOS X
Classifier: Environment :: Win32 (MS Windows)
Classifier: Environment :: X11 Applications
Classifier: License :: OSI Approved :: BSD License
Classifier: Operating System :: MacOS :: MacOS X
Classifier: Operating System :: Microsoft :: Windows
Classifier: Operating System :: POSIX :: Linux
Classifier: Programming Language :: Python :: 3
Classifier: Programming Language :: Python :: 3.8
Classifier: Programming Language :: Python :: 3.9
Classifier: Programming Language :: Python :: 3.10
Classifier: Programming Language :: Python :: 3.11
Classifier: Topic :: Games/Entertainment
Requires-Python: >=3.6
License-File: LICENSE
